{"cameraMode":{"drawMode":0,"name":"Shaded","section":"Shading Mode"},"sceneLighting":false,"audioPlay":false,"sceneViewState":{"m_AlwaysRefresh":false,"showFog":true,"showSkybox":true,"showFlares":true,"showImageEffects":true,"showParticleSystems":true,"showVisualEffectGraphs":true,"m_FxEnabled":true},"in2DMode":false,"pivot":{"x":75.95561218261719,"y":43.5164794921875,"z":151.48602294921876},"rotation":{"x":-0.1780819147825241,"y":0.7732083201408386,"z":-0.24831369519233704,"w":-0.5558764934539795},"size":10.0,"orthographic":false}